{"localities":[{"id":11333,"name":"Adancata"},{"id":11334,"name":"Antoceni"},{"id":11335,"name":"Arbore"},{"id":11336,"name":"Argel"},{"id":11337,"name":"Argestru"},{"id":11338,"name":"Arghira"},{"id":11339,"name":"Artari"},{"id":11340,"name":"Badeuti"},{"id":11341,"name":"Badragi"},{"id":11342,"name":"Bahna Arin"},{"id":11343,"name":"Baia"},{"id":11344,"name":"Bainet"},{"id":11345,"name":"Baisesti"},{"id":11346,"name":"Balaceana"},{"id":11347,"name":"Balcauti"},{"id":11348,"name":"Balinesti"},{"id":11349,"name":"Bancesti"},{"id":11350,"name":"Banesti"},{"id":11351,"name":"Barasti"},{"id":11352,"name":"Basarabi"},{"id":11353,"name":"Benia"},{"id":11354,"name":"Berchisesti"},{"id":11355,"name":"Beresti"},{"id":11356,"name":"Bilca"},{"id":11357,"name":"Bivolaria"},{"id":11358,"name":"Bobeica"},{"id":11359,"name":"Bodnareni"},{"id":11360,"name":"Bogata"},{"id":11361,"name":"Bogdanesti"},{"id":11362,"name":"Boroaia"},{"id":11363,"name":"Bosanci"},{"id":11364,"name":"Botesti"},{"id":11365,"name":"Botos"},{"id":11366,"name":"Botosana"},{"id":11367,"name":"Botosanita Mare"},{"id":11368,"name":"Botosanita Mica"},{"id":11369,"name":"Botus"},{"id":11370,"name":"Botusel"},{"id":11371,"name":"Boura"},{"id":11372,"name":"Bradatel"},{"id":11373,"name":"Braiesti"},{"id":11374,"name":"Branistea"},{"id":11375,"name":"Brasca"},{"id":11377,"name":"Breaza"},{"id":11376,"name":"Breaza de Sus"},{"id":11380,"name":"Brodina"},{"id":11378,"name":"Brodina de Jos"},{"id":11379,"name":"Brodina(Izvoarele Sucevei)"},{"id":11382,"name":"Brosteni"},{"id":11381,"name":"Brosteni(Draguseni)"},{"id":11383,"name":"Bucsoaia"},{"id":11384,"name":"Buda(Rasca)"},{"id":11385,"name":"Buda(Zvoristea)"},{"id":11386,"name":"Budeni"},{"id":11387,"name":"Bulai"},{"id":11388,"name":"Bunesti"},{"id":11389,"name":"Burla"},{"id":11390,"name":"Bursuceni"},{"id":11391,"name":"Cacica"},{"id":11392,"name":"Cajvana"},{"id":11393,"name":"Calafindesti"},{"id":11396,"name":"Calinesti-Vasilache"},{"id":11394,"name":"Calinesti(Darmanesti)"},{"id":11395,"name":"Calinesti(Serbauti)"},{"id":11397,"name":"Calugareni"},{"id":11398,"name":"Camarzani"},{"id":11399,"name":"Campulung Moldovenesc"},{"id":11400,"name":"Capu Campului"},{"id":11401,"name":"Capu Codrului"},{"id":11403,"name":"Carlibaba"},{"id":11402,"name":"Carlibaba Noua"},{"id":11404,"name":"Casoi"},{"id":11744,"name":"Catrinari"},{"id":11405,"name":"Chiliseni"},{"id":11406,"name":"Chiril"},{"id":11407,"name":"Ciocanesti"},{"id":11408,"name":"Ciomartan"},{"id":11409,"name":"Ciprian Porumbescu"},{"id":11410,"name":"Ciumarna"},{"id":11411,"name":"Ciumulesti"},{"id":11412,"name":"Climauti"},{"id":11413,"name":"Clit"},{"id":11414,"name":"Codru"},{"id":11415,"name":"Cojocareni"},{"id":11416,"name":"Cojoci"},{"id":11417,"name":"Colacu"},{"id":11418,"name":"Comanesti"},{"id":11419,"name":"Corlata"},{"id":11420,"name":"Corni"},{"id":11421,"name":"Cornu Luncii"},{"id":11422,"name":"Corocaiesti"},{"id":11423,"name":"Corpaci"},{"id":11424,"name":"Cosna"},{"id":11425,"name":"Costana"},{"id":11426,"name":"Costileva"},{"id":11427,"name":"Costisa"},{"id":11428,"name":"Cotargasi"},{"id":11429,"name":"Cotu Baii"},{"id":11430,"name":"Cotu Dobei"},{"id":11431,"name":"Coverca"},{"id":11432,"name":"Cozanesti"},{"id":11433,"name":"Crucea"},{"id":11434,"name":"Cumparatura"},{"id":11736,"name":"Cununschi"},{"id":11435,"name":"Danila"},{"id":11436,"name":"Darmanesti"},{"id":11437,"name":"Darmoxa"},{"id":11439,"name":"Dealu"},{"id":11438,"name":"Dealu Floreni"},{"id":11440,"name":"Deia"},{"id":11441,"name":"Deleni"},{"id":11442,"name":"Delnita"},{"id":11443,"name":"Delut"},{"id":11444,"name":"Demacusa"},{"id":11445,"name":"Dolhasca"},{"id":11446,"name":"Dolhesti"},{"id":11447,"name":"Dolhestii Mari"},{"id":11448,"name":"Dolhestii Mici"},{"id":11449,"name":"Dorna Candrenilor"},{"id":11450,"name":"Dorna-Arini"},{"id":11451,"name":"Dornesti"},{"id":11452,"name":"Dornisoara"},{"id":11453,"name":"Doroteia"},{"id":11454,"name":"Dragoiasa"},{"id":11455,"name":"Dragoiesti"},{"id":11456,"name":"Dragomirna"},{"id":11457,"name":"Dragosa"},{"id":11458,"name":"Draguseni"},{"id":11459,"name":"Dubiusca"},{"id":11460,"name":"Dumbrava(Cornu Luncii)"},{"id":11461,"name":"Dumbrava(Granicesti)"},{"id":11463,"name":"Dumbraveni"},{"id":11462,"name":"Dumbraveni(Rasca)"},{"id":11464,"name":"Dumbravita"},{"id":11737,"name":"Ehreste"},{"id":11465,"name":"Falcau"},{"id":11466,"name":"Falticeni"},{"id":11467,"name":"Fantana Mare"},{"id":11468,"name":"Fantanele"},{"id":11469,"name":"Fetesti"},{"id":11470,"name":"Florinta"},{"id":11471,"name":"Forasti"},{"id":11473,"name":"Frasin"},{"id":11472,"name":"Frasin(Brosteni)"},{"id":11474,"name":"Fratautii Noi"},{"id":11475,"name":"Fratautii Vechi"},{"id":11476,"name":"Frumoasa"},{"id":11477,"name":"Frumosu"},{"id":11478,"name":"Fundu Moldovei"},{"id":11479,"name":"Gainesti"},{"id":11480,"name":"Galanesti"},{"id":11482,"name":"Gara"},{"id":11481,"name":"Gara Leu"},{"id":11483,"name":"Gemenea"},{"id":11484,"name":"Gheorghiteni"},{"id":11485,"name":"Giulesti"},{"id":11486,"name":"Giurgesti"},{"id":11487,"name":"Glodu"},{"id":11488,"name":"Gramesti"},{"id":11489,"name":"Granicesti"},{"id":11490,"name":"Grigoresti"},{"id":11491,"name":"Groapa Vladichii"},{"id":11492,"name":"Gropeni"},{"id":11493,"name":"Gulia"},{"id":11494,"name":"Gura Haitii"},{"id":11495,"name":"Gura Humorului"},{"id":11496,"name":"Gura Putnei"},{"id":11497,"name":"Gura Solcii"},{"id":11738,"name":"Haleasa"},{"id":11498,"name":"Hancea"},{"id":11499,"name":"Hantesti"},{"id":11500,"name":"Hartop"},{"id":11501,"name":"Herla"},{"id":11502,"name":"Holda"},{"id":11503,"name":"Holdita"},{"id":11506,"name":"Horodnic"},{"id":11504,"name":"Horodnic de Jos"},{"id":11505,"name":"Horodnic de Sus"},{"id":11507,"name":"Horodniceni"},{"id":11508,"name":"Hreatca"},{"id":11509,"name":"Humoreni"},{"id":11510,"name":"Hurjuieni"},{"id":11511,"name":"Husi"},{"id":11512,"name":"Iacobeni"},{"id":11513,"name":"Iacobesti"},{"id":11514,"name":"Iaslovat"},{"id":11515,"name":"Iaz"},{"id":11740,"name":"Iedu"},{"id":11516,"name":"Iesle"},{"id":11517,"name":"Ilisesti"},{"id":11518,"name":"Ioneasa"},{"id":11519,"name":"Ipotesti"},{"id":11520,"name":"Izvoarele Sucevei"},{"id":11521,"name":"Jacota"},{"id":11522,"name":"Jahalia"},{"id":11523,"name":"Lamaseni"},{"id":11524,"name":"Leucusesti"},{"id":11525,"name":"Lipoveni"},{"id":11526,"name":"Lisaura"},{"id":11528,"name":"Liteni"},{"id":11527,"name":"Liteni(Moara)"},{"id":11529,"name":"Lucacesti"},{"id":11530,"name":"Lunca(Milisauti)"},{"id":11531,"name":"Lunca(Zamostea)"},{"id":11532,"name":"Luncusoara"},{"id":11533,"name":"Lungeni"},{"id":11534,"name":"Lupcina"},{"id":11535,"name":"Magura"},{"id":11536,"name":"Maidan"},{"id":11537,"name":"Malini"},{"id":11538,"name":"Manastioara(Siret)"},{"id":11539,"name":"Manastioara(Udesti)"},{"id":11540,"name":"Manastirea Humorului"},{"id":11541,"name":"Maneuti"},{"id":11542,"name":"Manolea"},{"id":11543,"name":"Marginea"},{"id":11544,"name":"Maritei"},{"id":11545,"name":"Mariteia Mica"},{"id":11546,"name":"Mazanaesti"},{"id":11547,"name":"Mereni"},{"id":11548,"name":"Meresti"},{"id":11549,"name":"Mestecanis"},{"id":11550,"name":"Mesteceni"},{"id":11551,"name":"Mihaiesti"},{"id":11552,"name":"Mihoveni"},{"id":11553,"name":"Milisauti"},{"id":11554,"name":"Mironu"},{"id":11555,"name":"Mitocasi"},{"id":11556,"name":"Mitocu Dragomirnei"},{"id":11559,"name":"Moara"},{"id":11557,"name":"Moara Carp"},{"id":11558,"name":"Moara Nica"},{"id":11560,"name":"Moisa"},{"id":11561,"name":"Moldova-Sulita"},{"id":11562,"name":"Moldovita"},{"id":11563,"name":"Molid"},{"id":11564,"name":"Movileni"},{"id":11565,"name":"Musenita"},{"id":11739,"name":"Neagra"},{"id":11566,"name":"Neagra Sarului"},{"id":11567,"name":"Negostina"},{"id":11568,"name":"Negrileasa"},{"id":11569,"name":"Nicani"},{"id":11570,"name":"Nigotesti"},{"id":11571,"name":"Nisipitu"},{"id":11572,"name":"Norocu"},{"id":11573,"name":"Obcina"},{"id":11574,"name":"Oniceni"},{"id":11575,"name":"Ortoaia"},{"id":11576,"name":"Osoi"},{"id":11577,"name":"Ostra"},{"id":11578,"name":"Padureni"},{"id":11579,"name":"Paiseni"},{"id":11580,"name":"Paltin"},{"id":11745,"name":"Paltinis"},{"id":11581,"name":"Paltinoasa"},{"id":11582,"name":"Paltinu"},{"id":11583,"name":"Panaci"},{"id":11584,"name":"Paraie"},{"id":11585,"name":"Parau Negrei"},{"id":11586,"name":"Parhauti"},{"id":11587,"name":"Partestii de Jos"},{"id":11588,"name":"Partestii de Sus"},{"id":11589,"name":"Patrauti"},{"id":11590,"name":"Petia"},{"id":11591,"name":"Pietroasa"},{"id":11592,"name":"Pilugani"},{"id":11593,"name":"Plai"},{"id":11594,"name":"Plaiu Sarului"},{"id":11595,"name":"Plavalari"},{"id":11596,"name":"Plesa"},{"id":11597,"name":"Plesesti"},{"id":11598,"name":"Plopeni"},{"id":11599,"name":"Plutonita"},{"id":11600,"name":"Pocoleni"},{"id":11601,"name":"Podeni"},{"id":11602,"name":"Podu Cosnei"},{"id":11603,"name":"Poiana Marului"},{"id":11604,"name":"Poiana Micului"},{"id":11605,"name":"Poiana Negrii"},{"id":11606,"name":"Poiana Stampei"},{"id":11607,"name":"Poiana(Dolhasca)"},{"id":11608,"name":"Poiana(Zvoristea)"},{"id":11609,"name":"Poienari"},{"id":11610,"name":"Poieni-Solca"},{"id":11611,"name":"Poieni-Suceava"},{"id":11612,"name":"Pojorata"},{"id":11746,"name":"Praleni"},{"id":11613,"name":"Praxia"},{"id":11614,"name":"Prelipca"},{"id":11615,"name":"Preutesti"},{"id":11616,"name":"Prisaca Dornei"},{"id":11617,"name":"Probota"},{"id":11618,"name":"Putna"},{"id":11619,"name":"Racova"},{"id":11620,"name":"Radaseni"},{"id":11621,"name":"Radauti"},{"id":11733,"name":"Rasca"},{"id":13905,"name":"Rasca(Moldovita)"},{"id":11622,"name":"Rauteni"},{"id":11623,"name":"Reuseni"},{"id":11743,"name":"Romanesti(Cosna)"},{"id":11624,"name":"Romanesti(Granicesti)"},{"id":11625,"name":"Roscani"},{"id":11626,"name":"Rosiori"},{"id":11627,"name":"Rosu"},{"id":11628,"name":"Rotopanesti"},{"id":11629,"name":"Rotunda"},{"id":11630,"name":"Rudesti"},{"id":11631,"name":"Runcu"},{"id":11632,"name":"Rusca"},{"id":11633,"name":"Rusi"},{"id":11634,"name":"Rusii-Manastioara"},{"id":11635,"name":"Sacuta"},{"id":11636,"name":"Sadau"},{"id":11637,"name":"Sadova"},{"id":11638,"name":"Salageni"},{"id":11639,"name":"Salcea"},{"id":11640,"name":"Sarghiesti"},{"id":11641,"name":"Sarisor"},{"id":11642,"name":"Sarisoru Mare"},{"id":11643,"name":"Saru Bucovinei"},{"id":11644,"name":"Saru Dornei"},{"id":11645,"name":"Sasca Mare"},{"id":11646,"name":"Sasca Mica"},{"id":11647,"name":"Sasca Noua"},{"id":11649,"name":"Satu Mare"},{"id":11648,"name":"Satu Mare(Crucea)"},{"id":11650,"name":"Scheia"},{"id":11651,"name":"Securiceni"},{"id":11652,"name":"Serbanesti"},{"id":11653,"name":"Serbauti"},{"id":11654,"name":"Ses"},{"id":11741,"name":"Sesuri"},{"id":11655,"name":"Sfantu Ilie"},{"id":11657,"name":"Silistea"},{"id":11656,"name":"Silistea Noua"},{"id":11658,"name":"Siminicea"},{"id":11659,"name":"Sinca"},{"id":11660,"name":"Siret"},{"id":11661,"name":"Slatina"},{"id":11662,"name":"Slatioara(Rasca)"},{"id":11663,"name":"Slatioara(Stulpicani)"},{"id":11664,"name":"Slobozia Sucevei"},{"id":11665,"name":"Slobozia(Fantanele)"},{"id":11666,"name":"Slobozia(Zvoristea)"},{"id":11667,"name":"Smida Ungurenilor"},{"id":11668,"name":"Solca"},{"id":11669,"name":"Soldanesti"},{"id":11670,"name":"Solonet"},{"id":11671,"name":"Solonetu Nou"},{"id":11672,"name":"Spataresti"},{"id":11673,"name":"Stamate"},{"id":11674,"name":"Stanca"},{"id":11675,"name":"Stancuta"},{"id":11676,"name":"Stirbat"},{"id":11677,"name":"Straja"},{"id":11678,"name":"Stramtura"},{"id":11679,"name":"Stroiesti"},{"id":11680,"name":"Stulpicani"},{"id":11681,"name":"Suceava"},{"id":11682,"name":"Sucevita"},{"id":11683,"name":"Sunatori"},{"id":11684,"name":"Tarna Mare"},{"id":11685,"name":"Tarnicioara"},{"id":11686,"name":"Tataru"},{"id":11687,"name":"Tautesti"},{"id":11688,"name":"Tesna(Cosna)"},{"id":11689,"name":"Tesna(Poiana Stampei)"},{"id":11742,"name":"Tibau"},{"id":11690,"name":"Tibeni"},{"id":11691,"name":"Tisauti"},{"id":11735,"name":"Todireni"},{"id":11692,"name":"Todiresti"},{"id":11693,"name":"Tolesti"},{"id":11694,"name":"Trei Movile"},{"id":11695,"name":"Udesti"},{"id":11696,"name":"Uidesti"},{"id":11697,"name":"Ulma"},{"id":11698,"name":"Uncesti"},{"id":11699,"name":"Vadu Moldovei"},{"id":11700,"name":"Vadu Negrilesei"},{"id":11701,"name":"Valcelele"},{"id":11702,"name":"Valea Bancului"},{"id":11703,"name":"Valea Bourei"},{"id":11704,"name":"Valea Glodului"},{"id":11705,"name":"Valea Moldovei"},{"id":11706,"name":"Valea Poienei"},{"id":11707,"name":"Valea Putnei"},{"id":11708,"name":"Valea Stanei"},{"id":11709,"name":"Valeni-Stanisoara"},{"id":11710,"name":"Vama"},{"id":11711,"name":"Varatec"},{"id":11712,"name":"Varfu Dealului"},{"id":11734,"name":"Varvata"},{"id":11713,"name":"Vascauti"},{"id":11714,"name":"Vatra Dornei"},{"id":11715,"name":"Vatra Moldovitei"},{"id":11716,"name":"Verbia"},{"id":11717,"name":"Vercicani"},{"id":11718,"name":"Veresti"},{"id":11719,"name":"Vicovu de Jos"},{"id":11720,"name":"Vicovu de Sus"},{"id":11721,"name":"Vicsani"},{"id":11722,"name":"Voievodeasa"},{"id":11723,"name":"Voitinel"},{"id":11724,"name":"Volovat"},{"id":11725,"name":"Vornicenii Mari"},{"id":11726,"name":"Vornicenii Mici"},{"id":11727,"name":"Voronet"},{"id":11728,"name":"Vulturesti"},{"id":11729,"name":"Zaharesti"},{"id":11730,"name":"Zalomestra"},{"id":11731,"name":"Zamostea"},{"id":11732,"name":"Zvoristea"}]}